DFirebase/__init__.py
DFirebase/Browser.py
DFirebase/Email.py
DFirebase/Firebase.py
DFirebase/GAuth.py
DFirebase/SSEClient.py
dfirebase-0.0.4.dist-info/WHEEL
dfirebase-0.0.4.dist-info/METADATA
dfirebase-0.0.4.dist-info/RECORD
