Metadata-Version: 2.1
Name: dfirebase
Version: 0.0.4
Summary: 
Author: DesKaOne
Requires-Python: >=3.8,<4.0
Classifier: Programming Language :: Python :: 3
Classifier: Programming Language :: Python :: 3.8
Classifier: Programming Language :: Python :: 3.9
Classifier: Programming Language :: Python :: 3.10
Classifier: Programming Language :: Python :: 3.11
Requires-Dist: blinker (>=1.4.0)
Requires-Dist: bs4 (>=0.0.1,<0.0.2)
Requires-Dist: cryptography (>=3.0.0)
Requires-Dist: deskaone-requests (>=0.0.6,<0.0.7)
Requires-Dist: gcloud (>=0.18.3)
Requires-Dist: google-api-python-client (>=2.97.0,<3.0.0)
Requires-Dist: google-auth-httplib2 (>=0.1.0,<0.2.0)
Requires-Dist: google-auth-oauthlib (>=1.0.0,<2.0.0)
Requires-Dist: oauth2client (>=4.1.2)
Requires-Dist: pycryptodome (>=3.6.4)
Requires-Dist: pyjwt (>=2.0.0,<3)
Requires-Dist: python-jwt (>=2.0.1)
Requires-Dist: requests-toolbelt (>=0.7.1,<1.0)
Requires-Dist: requests[socks] (>=2.11.1,<3.0.0)
Requires-Dist: urllib3 (>=1.21.1,<2)
